ncplib/__init__.py
ncplib/client.py
ncplib/connection.py
ncplib/errors.py
ncplib/http.py
ncplib/packets.py
ncplib/py.typed
ncplib/server.py
ncplib/values.py
ncplib-6.1.0.dist-info/LICENSE
ncplib-6.1.0.dist-info/METADATA
ncplib-6.1.0.dist-info/WHEEL
ncplib-6.1.0.dist-info/top_level.txt
ncplib-6.1.0.dist-info/RECORD
