Metadata-Version: 2.1
Name: ncplib
Version: 6.1.0
Summary: CRFS NCP library for Python 3.
Home-page: https://github.com/CRFS/python3-ncplib
Author: Dave Hall
Author-email: dhall@crfs.com
License: BSD
Platform: UNKNOWN
Classifier: Development Status :: 5 - Production/Stable
Classifier: Environment :: Web Environment
Classifier: Intended Audience :: Developers
Classifier: Operating System :: OS Independent
Classifier: Programming Language :: Python
Classifier: Programming Language :: Python :: 3.7
Classifier: Programming Language :: Python :: 3.8
Classifier: Programming Language :: Python :: 3.9
Classifier: Programming Language :: Python :: 3.10
License-File: LICENSE
Requires-Dist: async-timeout (<5.0,>=3.0)
